Metadata-Version: 2.1
Name: MathLibrary
Version: 20.0
Summary: Math Library For Python
Home-page: https://github.com/abdulsamedkeskin/MathLibrary
Author: Abdulsamet Keskin
Author-email: erdemsametkeskin25@gmail.com
License: MIT
Download-URL: https://github.com/abdulsamedkeskin/MathLibrary/archive/V20.tar.gz
Keywords: MathLibrary
Platform: UNKNOWN
Classifier: Development Status :: 3 - Alpha
Classifier: Intended Audience :: Developers
Classifier: Topic :: Software Development :: Build Tools
Classifier: License :: OSI Approved :: MIT License
Classifier: Programming Language :: Python :: 3
Classifier: Programming Language :: Python :: 3.4
Classifier: Programming Language :: Python :: 3.5
Classifier: Programming Language :: Python :: 3.6
